Workbook

Sheet Summary
A2: Simple business budget
A4: Business name
A5: Budget period | D5: Enter the month or period covered, e.g. October 2026.
A6: Currency | B6: IQD | D6: Use one currency throughout. Changing this label does not convert amounts.
A8: Budget status | B8: =IF(COUNT(Revenue!B10:B29,'Direct Costs'!B10:B29,'Indirect Expenses'!B10:B29)=0,"Enter budget figures","Budget entered") -> Budget entered
A10: Budget summary | B10: Amount
A11: Total revenue | B11: =Revenue!B31 -> 8000000 | D11: Expected income from selling products or providing services.
A12: Less: direct costs | B12: ='Direct Costs'!B31 -> 3000000 | D12: Costs directly related to those products or services.
A14: Gross profit | B14: =B11-B12 -> 5000000 | D14: Revenue minus direct costs.
A16: Less: indirect and other expenses | B16: ='Indirect Expenses'!B31 -> 2500000 | D16: Business overheads, plus interest and income tax if applicable.
A18: Net profit / (loss) | B18: =B14-B16 -> 2500000 | D18: Gross profit minus indirect and other expenses.
A20: Gross profit margin | B20: =IF(B11=0,"n.a.",B14/B11) -> 0.625
A21: Net profit margin | B21: =IF(B11=0,"n.a.",B18/B11) -> 0.3125
A24: How to use
A25: 1. Enter budget amounts in the yellow cells on the three input tabs.
A26: 2. Use the same period and currency for all figures. Enter costs as positive amounts.
A27: 3. Return here to see the automatic summary. Blank amount cells count as zero.
A28: Each input tab has 20 lines. Rename the suggested categories to fit your business.
A29: Asset purchases are listed separately below for donor review; they are excluded from the profit calculation above.
A31: DONOR BUDGET SUMMARY
A33: Direct project costs | B33: =B12 -> 3000000
A34: Indirect and other expenses | B34: =B16 -> 2500000
A35: Less: depreciation (non-cash) | B35: =IF('Indirect Expenses'!B19="",0,'Indirect Expenses'!B19) -> 0 | D35: Excludes the Depreciation line on Indirect Expenses to avoid double-counting asset costs.
A36: Operating budget excluding depreciation | B36: =B33+B34-B35 -> 5500000
A38: Asset purchases (CAPEX) | B38: ='Asset Purchases'!D27 -> 3000000 | D38: Full purchase cost from Asset Purchases, including the stated quantities and unit costs.
A40: TOTAL PROJECT BUDGET | B40: =IF(ISNUMBER(B38),SUM(B36,B38),"Complete asset rows") -> 8500000
A42: Less: other confirmed funding | D42: Enter owner contributions, other grants and project revenue committed to this budget.
A44: FUNDING NEEDED FROM DONOR | B44: =IF(ISNUMBER(B40),MAX(0,B40-B42),"Complete asset rows") -> 8500000 | D44: Total project budget less other confirmed funding, with a minimum of zero.
A46: Donor budget basis: planned costs for the stated project period; this is not a payment-timing cash forecast.
A47: Revenue is not automatically deducted as funding. Include only revenue committed to the project in other confirmed funding.
A48: Confirm donor eligibility of each cost, including interest and tax. Put depreciation only on the designated Depreciation line.

Sheet Revenue
A2: Revenue
A4: Budget period | B4: =IF(Summary!B5="","Enter on Summary",Summary!B5) -> Enter on Summary
A5: Currency | B5: =Summary!B6 -> IQD
A7: Enter your expected revenue. Rename or add items in the yellow rows.
A8: Blank amounts count as zero. Notes can explain your estimate, e.g. 100 units × 5,000 IQD.
A9: Budget item | B9: Budget amount | D9: Notes / basis of estimate
A10: Product sales | B10: 8000000 | D10: Expected sales of products.
A11: Service income | D11: Expected fees for your services.
A12: Other operating revenue | D12: Other income from normal business activities.
A31: Total revenue | B31: =SUM(B10:B29) -> 8000000
A33: Only yellow cells need input. The total above flows automatically to Summary.

Sheet Direct Costs
A2: Direct Costs
A4: Budget period | B4: =IF(Summary!B5="","Enter on Summary",Summary!B5) -> Enter on Summary
A5: Currency | B5: =Summary!B6 -> IQD
A7: Enter positive budgeted costs. List each expense only once across the cost tabs.
A8: Blank amounts count as zero. Notes can explain your estimate, e.g. 100 units × 5,000 IQD.
A9: Budget item | B9: Budget amount | D9: Notes / basis of estimate
A10: Materials / ingredients used | B10: 3000000 | D10: Cost of materials used for the budgeted sales.
A11: Vip Dress | D11: Cost of the goods expected to be sold, not all stock purchases.
A12: Direct production labour | D12: Labour directly attributable to making products or delivering services.
A13: Packaging used for sales | D13: Packaging consumed for the budgeted sales.
A14: Other direct costs | D14: Other costs directly attributable to products or services.
A31: Total direct costs | B31: =SUM(B10:B29) -> 3000000
A33: Only yellow cells need input. The total above flows automatically to Summary.

Sheet Indirect Expenses
A2: Indirect Expenses
A4: Budget period | B4: =IF(Summary!B5="","Enter on Summary",Summary!B5) -> Enter on Summary
A5: Currency | B5: =Summary!B6 -> IQD
A7: Enter positive budgeted costs. List each expense only once across the cost tabs.
A8: Blank amounts count as zero. Notes can explain your estimate, e.g. 100 units × 5,000 IQD.
A9: Budget item | B9: Budget amount | D9: Notes / basis of estimate
A10: Rent | B10: 2500000 | D10: Rent for 5 month
A11: Administrative salaries | D11: Support staff salaries; exclude labour already listed as direct costs.
A12: Electricity and water | D12: Utilities treated as overhead in this simple template.
A13: Marketing and advertising | D13: Promotion and advertising.
A14: Internet and telephone | D14: Business communications.
A15: Transport and delivery overhead | D15: Delivery or transport treated as overhead; do not double-count direct costs.
A16: Repairs and maintenance | D16: Routine repairs and upkeep.
A17: Insurance and licences | D17: Only the amount relating to this budget period.
A18: Office supplies | D18: Stationery and other office supplies.
A19: Depreciation | D19: The period’s depreciation expense, not the equipment purchase price.
A20: Other operating expenses | D20: Other overheads not already listed.
A21: Interest expense | D21: Interest only; exclude loan principal repayments.
A22: Income tax expense | D22: Enter an estimate if applicable; this workbook does not calculate tax.
A31: Total indirect expenses | B31: =SUM(B10:B29) -> 2500000
A33: Only yellow cells need input. The total above flows automatically to Summary.
A34: Interest and income tax are included here separately so the summary can show net profit.

Sheet Asset Purchases
A2: Asset purchases (CAPEX)
A4: Budget period | B4: =IF(Summary!B5="","Enter on Summary",Summary!B5) -> Enter on Summary
A5: Currency | B5: =Summary!B6 -> IQD
A7: List the full purchase cost of equipment, furniture and other long-term assets needed for the project.
A8: Yellow cells are inputs. Explain why each asset is needed so the donor can review the request.
A10: Asset / equipment | B10: Quantity | C10: Unit cost | D10: Total purchase cost | E10: Purpose / justification
A11: Sewing machine | B11: 2 | C11: =1000*1500 -> 1500000 | D11: =IF(COUNTA(A11:C11,E11)=0,"",IF(OR(A11="",B11="",C11="",E11=""),"Complete row",B11*C11)) -> 3000000 | E11: I need to expand my work, be able to produce more dresses
D12: =IF(COUNTA(A12:C12,E12)=0,"",IF(OR(A12="",B12="",C12="",E12=""),"Complete row",B12*C12))
D13: =IF(COUNTA(A13:C13,E13)=0,"",IF(OR(A13="",B13="",C13="",E13=""),"Complete row",B13*C13))
D14: =IF(COUNTA(A14:C14,E14)=0,"",IF(OR(A14="",B14="",C14="",E14=""),"Complete row",B14*C14))
D15: =IF(COUNTA(A15:C15,E15)=0,"",IF(OR(A15="",B15="",C15="",E15=""),"Complete row",B15*C15))
D16: =IF(COUNTA(A16:C16,E16)=0,"",IF(OR(A16="",B16="",C16="",E16=""),"Complete row",B16*C16))
D17: =IF(COUNTA(A17:C17,E17)=0,"",IF(OR(A17="",B17="",C17="",E17=""),"Complete row",B17*C17))
D18: =IF(COUNTA(A18:C18,E18)=0,"",IF(OR(A18="",B18="",C18="",E18=""),"Complete row",B18*C18))
D19: =IF(COUNTA(A19:C19,E19)=0,"",IF(OR(A19="",B19="",C19="",E19=""),"Complete row",B19*C19))
D20: =IF(COUNTA(A20:C20,E20)=0,"",IF(OR(A20="",B20="",C20="",E20=""),"Complete row",B20*C20))
D21: =IF(COUNTA(A21:C21,E21)=0,"",IF(OR(A21="",B21="",C21="",E21=""),"Complete row",B21*C21))
D22: =IF(COUNTA(A22:C22,E22)=0,"",IF(OR(A22="",B22="",C22="",E22=""),"Complete row",B22*C22))
D23: =IF(COUNTA(A23:C23,E23)=0,"",IF(OR(A23="",B23="",C23="",E23=""),"Complete row",B23*C23))
... D25: =IF(COUNTA(A25:C25,E25)=0,"",IF(OR(A25="",B25="",C25="",E25=""),"Complete row",B25*C25))
A27: Total asset purchases | D27: =IF(COUNTIFS(D11:D25,"Complete row")>0,"Complete asset rows",SUM(D11:D25)) -> 3000000
A29: Examples: coffee machine, laptop, refrigerator, desks or production equipment.
A30: Include delivery and installation in unit cost when part of the asset’s purchase cost.
A31: Full asset cost goes to the donor budget. Only depreciation goes to the profit summary.
A32: State useful quantities and costs for this project only. Do not enter the same purchase under Direct Costs or Indirect Expenses.
